Workbook

Sheet Gates
A2: MatriSathi stage gates
A3: Day 1 = agreed kickoff. Counts do not approve gates. Amber cells require human input.
A4: Version 1.1: detailed build requirements are in Functional Specs and Technical Specs. Gate IDs SG0–SG7 are milestones; F/T IDs are specs; R IDs are shared requirements.
A6: Gate | B6: Day | C6: Milestone | D6: Demonstrate | E6: Exit criteria | F6: Required reviewers | G6: Evidence pack | H6: Outcome | I6: Decision by / date | J6: Evidence link | K6: Tasks | L6: Verified done | M6: Functional spec IDs | N6: Technical spec IDs
A7: SG0 | B7: 2 | C7: Kickoff and working agreement | D7: Baseline, roles, capacity, repository workflow and clinical owners agreed. | E7: Approve scope amendments, decision owners, weekly hours and first slice. Repository setup evidenced or a named blocker recorded. | F7: Team lead + Tech lead | G7: Baseline files; decision log; owner list; approved next-stage scope. | H7: Pending | K7: =COUNTIF(Tasks!$C$7:$C$68,A7) | L7: =SUMIF(Tasks!$C$7:$C$68,A7,Tasks!$Q$7:$Q$68) | M7: F001 | N7: T001
A8: SG1 | B8: 7 | C8: Independent foundation | D8: Browser login, mother registration and pregnancy creation survive reload/restart. | E8: AT01–AT05 pass; two organizations tested; clean setup and CI evidence; first slice reviewed. | F8: Tech lead + Team lead | G8: Commit SHA; CI output; synthetic browser demo; schema/permission review. | H8: Pending | K8: =COUNTIF(Tasks!$C$7:$C$68,A8) | L8: =SUMIF(Tasks!$C$7:$C$68,A8,Tasks!$Q$7:$Q$68) | M8: F002–F004 | N8: T002–T007
A9: SG2 | B9: 14 | C9: Pregnancy care and next actions | D9: Approved ANC plan, birth preparation, tasks, private records and safe patient access work. | E9: AT06–AT10 and AT28 pass; doctor validates journey and schedule; uploaded report is not marked reviewed. | F9: Team lead + Doctor + Tech lead | G9: Clinical version approvals; task/referral demo; private-file access tests. | H9: Pending | K9: =COUNTIF(Tasks!$C$7:$C$68,A9) | L9: =SUMIF(Tasks!$C$7:$C$68,A9,Tasks!$Q$7:$Q$68) | M9: F005–F015, F044 | N9: T008–T010
A10: SG3 | B10: 21 | C10: Real WhatsApp and voice | D10: Actual outbound template plus inbound text, audio and photo reach a staffed test inbox. | E10: AT11–AT14 pass on consenting staff test numbers; retries, opt-out and recipient ambiguity demonstrated. | F10: Tech lead + Team lead + Doctor | G10: Provider configuration record without secrets; message IDs/statuses; audio demo; failure rehearsal. | H10: Pending | K10: =COUNTIF(Tasks!$C$7:$C$68,A10) | L10: =SUMIF(Tasks!$C$7:$C$68,A10,Tasks!$Q$7:$Q$68) | M10: F016–F020 | N10: T011–T013
A11: SG4 | B11: 28 | C11: Birth and early postpartum | D11: Separate mother/baby events, twins, discharge, loss pause and transfer work. | E11: AT15–AT18 and AT29 pass; maternal and pediatric reviewers validate event handling. | F11: Doctor + Pediatric reviewer + Tech lead | G11: Twin/loss/transfer scenarios; clinical approvals; task handover evidence. | H11: Pending | K11: =COUNTIF(Tasks!$C$7:$C$68,A11) | L11: =SUMIF(Tasks!$C$7:$C$68,A11,Tasks!$Q$7:$Q$68) | M11: F021–F028 | N11: T014–T015
A12: SG5 | B12: 42 | C12: Complete MVP scope | D12: All eight journey stages and R01–R12 functionality implemented; release hardening continues. | E12: AT01–AT23 and AT28–AT32 pass; all 12 audio topics approved; all mandatory scope mapped. | F12: Team lead + Doctor/Pediatric reviewer + Tech lead | G12: Traceability matrix; full journey demo; regression; content approvals; open-defect list. | H12: Pending | K12: =COUNTIF(Tasks!$C$7:$C$68,A12) | L12: =SUMIF(Tasks!$C$7:$C$68,A12,Tasks!$Q$7:$Q$68) | M12: F029–F040 | N12: T016–T020
A13: SG6 | B13: 49 | C13: Field validation and resilience | D13: Representative rural/semi-urban users complete core tasks; restore and failure drills run. | E13: AT24–AT27 pass; at least 5/6 users succeed with intended assistance and no safety-critical misunderstanding. | F13: Team lead + Tech lead + Tester + Doctor | G13: Observed user results; measured load/network report; restore/rollback evidence; retests. | H13: Pending | K13: =COUNTIF(Tasks!$C$7:$C$68,A13) | L13: =SUMIF(Tasks!$C$7:$C$68,A13,Tasks!$Q$7:$Q$68) | M13: F041–F042 | N13: T021–T022
A14: SG7 | B14: 56 | C14: Pilot-deployable release | D14: Release candidate has complete evidence, operating owners and a reproducible deployment. | E14: AT01–AT32 pass for candidate or valid unchanged evidence; no critical/high defects; three separate sign-offs. | F14: Team lead + Tech lead + Doctor/Pediatric reviewer + Facility owner | G14: Release SHA; checks and approvals; runbooks; roster; rollout/rollback and cost limits. | H14: Pending | K14: =COUNTIF(Tasks!$C$7:$C$68,A14) | L14: =SUMIF(Tasks!$C$7:$C$68,A14,Tasks!$Q$7:$Q$68) | M14: F043 | N14: T023

Sheet Tasks
A2: MatriSathi task backlog
A3: Version 1.0 | Estimates in hours. Issues/PRs own daily status; refresh this snapshot weekly.
A4: F IDs are detailed in Functional Specs; T IDs in Technical Specs. Filter by Gate or linked task. Existing hours and status fields are unchanged.
A6: ID | B6: Week | C6: Gate | D6: Owner | E6: Est. hours | F6: Task | G6: Dependencies | H6: Requirements | I6: Acceptance / evidence needed | J6: Reviewer | K6: Status | L6: Evidence link | M6: Review result | N6: Actual hours | O6: Issue / PR | P6: Actual reviewer | Q6: Verified done | R6: Detailed spec IDs
A7: M001 | B7: 1 | C7: SG0 | D7: Team lead | E7: 3 | F7: Confirm baseline, capacity and pilot setting | G7: None | H7: R09 R11 R12 | I7: Named owners; exact developer hours; two settings and language selected; amendments accepted. | J7: Tech lead | K7: Not started | M7: Pending | Q7: =IF(AND(K7="Done",M7="Accepted",LEN(L7)>0,LEN(P7)>0),1,0) | R7: F001, T001
A8: M002 | B8: 1 | C8: SG0 | D8: Tech lead | E8: 2 | F8: Shared repository and engineering agreement | G8: M001 | H8: R09 R10 | I8: Correct remote; protected-main proposal; task branches and approvals documented; secrets ignored. | J8: Team lead | K8: Not started | M8: Pending | Q8: =IF(AND(K8="Done",M8="Accepted",LEN(L8)>0,LEN(P8)>0),1,0) | R8: F001, T001, T007
A9: M003 | B9: 1 | C9: SG1 | D9: Tech lead | E9: 6 | F9: Review identity, auth, tenant and audit design | G9: M002 | H9: R02 R07 | I9: Unique staff login, org authority, session revocation and DB-role boundaries specified; AT01–AT04 design approved. | J9: Team lead | K9: Not started | M9: Pending | Q9: =IF(AND(K9="Done",M9="Accepted",LEN(L9)>0,LEN(P9)>0),1,0) | R9: F003, F004, T002, T003, T004, T005, T006
A10: M004 | B10: 1 | C10: SG1 | D10: Developer | E10: 7 | F10: Scaffold API, database and first migration | G10: M002 | H10: R02 R09 | I10: Clean local setup; Organization/Facility/Membership/Person/Contact/Episode migrations work. | J10: Tech lead | K10: Review | L10: docs/delivery/evidence/SG1/report.md | M10: Pending | Q10: =IF(AND(K10="Done",M10="Accepted",LEN(L10)>0,LEN(P10)>0),1,0) | R10: F002, T001, T002, T003, T007
A11: M005 | B11: 1 | C11: SG1 | D11: Developer | E11: 8 | F11: Implement staff login and scoped identity endpoints | G11: M003 M004 | H11: R02 R07 | I11: AT01–AT04 pass including existing-person link denial and restricted audit writes. | J11: Tech lead | K11: Review | L11: docs/delivery/evidence/SG1/report.md | M11: Pending | Q11: =IF(AND(K11="Done",M11="Accepted",LEN(L11)>0,LEN(P11)>0),1,0) | R11: F002, F003, F004, F037, T002, T003, T004, T005, T006
A12: M006 | B12: 1 | C12: SG1 | D12: Developer | E12: 7 | F12: Build registration UI and continuous checks | G12: M005 | H12: R09 R10 | I12: Browser login/register/create/view works; CI configured and run after authorized push; AT05 pass. | J12: Tech lead | K12: Review | L12: docs/delivery/evidence/SG1/report.md | M12: Pending | Q12: =IF(AND(K12="Done",M12="Accepted",LEN(L12)>0,LEN(P12)>0),1,0) | R12: F002, F003, T001, T007
A13: M007 | B13: 1 | C13: SG1 | D13: Team lead | E13: 4 | F13: Coordinate reviewer, language and messaging onboarding | G13: M001 | H13: R01 R06 R11 | I13: Provider comparison assigned; staff test numbers and account owner ready; content responsibilities assigned. | J13: Doctor | K13: Not started | M13: Pending | Q13: =IF(AND(K13="Done",M13="Accepted",LEN(L13)>0,LEN(P13)>0),1,0) | R13: F016
A14: M008 | B14: 1 | C14: SG1 | D14: Doctor | E14: 2 | F14: Validate intake, roles and journey coverage | G14: M001 | H14: Stages 1–8 R02 R05 | I14: Review notes identify required intake, role limits and pediatric reviewer. | J14: Team lead | K14: Not started | M14: Pending | Q14: =IF(AND(K14="Done",M14="Accepted",LEN(L14)>0,LEN(P14)>0),1,0) | R14: F002, F004
A15: M009 | B15: 2 | C15: SG2 | D15: Tech lead | E15: 5 | F15: Review plan/task states and private media controls | G15: M003 | H15: R03 R05 R07 | I15: State-specific permissions, versioned plan rules and private upload/download contract agreed. | J15: Doctor | K15: Not started | M15: Pending | Q15: =IF(AND(K15="Done",M15="Accepted",LEN(L15)>0,LEN(P15)>0),1,0) | R15: F005, F007, F008, F009, T002, T008, T009
A16: M010 | B16: 2 | C16: SG2 | D16: Tech lead | E16: 3 | F16: Approve patient/caregiver access mechanism | G16: M003 | H16: R02 R07 | I16: Shared-phone identity confirmation and revocation design reviewed; tests defined. | J16: Team lead | K16: Not started | M16: Pending | Q16: =IF(AND(K16="Done",M16="Accepted",LEN(L16)>0,LEN(P16)>0),1,0) | R16: F015, T005, T010
A17: M011 | B17: 2 | C17: SG2 | D17: Developer | E17: 8 | F17: ANC plan, appointments and owned tasks | G17: M005 M009 | H17: Stages 1–3 R03 R05 | I17: AT06 AT07 pass; next action and missed/rescheduled appointment demo works. | J17: Tech lead | K17: Not started | M17: Pending | Q17: =IF(AND(K17="Done",M17="Accepted",LEN(L17)>0,LEN(P17)>0),1,0) | R17: F005, F006, F007, F008, T008
A18: M012 | B18: 2 | C18: SG2 | D18: Developer | E18: 8 | F18: Reports, prescriptions and referral tracking | G18: M009 M011 | H18: Stage 2 R03 R07 | I18: AT08 AT09 pass; original records retained; clinical review restricted. | J18: Tech lead | K18: Not started | M18: Pending | Q18: =IF(AND(K18="Done",M18="Accepted",LEN(L18)>0,LEN(P18)>0),1,0) | R18: F009, F010, F011, F012, F044, T008, T009
A19: M013 | B19: 2 | C19: SG2 | D19: Developer | E19: 7 | F19: Patient next-action view and birth-plan screen | G19: M010 M011 | H19: Stage 3 R02 R06 | I19: AT10 AT28 pass; caregiver revoke blocks access; no-phone route usable. | J19: Tech lead | K19: Not started | M19: Pending | Q19: =IF(AND(K19="Done",M19="Accepted",LEN(L19)>0,LEN(P19)>0),1,0) | R19: F006, F013, F014, F015, F044, T010
A20: M014 | B20: 2 | C20: SG2 | D20: Team lead | E20: 6 | F20: Secure channel approval and prepare clinical content | G20: M007 | H20: R01 R06 R11 | I20: Provider decision/budget and account/template submission recorded; scripts prepared for review. | J20: Doctor | K20: Not started | M20: Pending | Q20: =IF(AND(K20="Done",M20="Accepted",LEN(L20)>0,LEN(P20)>0),1,0) | R20: F017
A21: M015 | B21: 2 | C21: SG2 | D21: Doctor | E21: 2 | F21: Approve pilot ANC template and urgent wording | G21: M008 M011 | H21: R05 R06 | I21: Versioned schedule, birth contacts wording and role limits approved or corrections assigned. | J21: Team lead | K21: Not started | M21: Pending | Q21: =IF(AND(K21="Done",M21="Accepted",LEN(L21)>0,LEN(P21)>0),1,0) | R21: F005, F012, F013, F014, F044
A22: M016 | B22: 2 | C22: SG2 | D22: Tester | E22: 4 | F22: Test foundation and antenatal slice | G22: M006 M013 | H22: AT01–AT10 AT28 | I22: Repeatable synthetic cases; failures logged with reproduction and evidence. | J22: Tech lead | K22: Not started | M22: Pending | Q22: =IF(AND(K22="Done",M22="Accepted",LEN(L22)>0,LEN(P22)>0),1,0) | R22: F007, F009, F011, F015
A23: M017 | B23: 3 | C23: SG3 | D23: Tech lead | E23: 5 | F23: Channel adapter, webhook and outbox design review | G23: M014 | H23: R01 R10 | I23: Authenticated webhook, durable send, dedup/retry and ambiguous-send contracts agreed; failure cases specified. | J23: Team lead | K23: Not started | M23: Pending | Q23: =IF(AND(K23="Done",M23="Accepted",LEN(L23)>0,LEN(P23)>0),1,0) | R23: F017, T011, T012
A24: M018 | B24: 3 | C24: SG3 | D24: Tech lead | E24: 3 | F24: Review media/privacy and inbox access | G24: M017 | H24: R01 R02 R07 | I24: Restricted queue, logging, media limits and patient-link authorization designed; access tests specified. | J24: Team lead | K24: Not started | M24: Pending | Q24: =IF(AND(K24="Done",M24="Accepted",LEN(L24)>0,LEN(P24)>0),1,0) | R24: F018, F019, T005, T009, T011, T013
... A68: M062 | B68: 8 | C68: SG7 | D68: Tester | E68: 8 | F68: Release acceptance and clean setup verification | G68: M057 M059 | H68: AT01–AT32 | I68: Mandatory cases passed/current; independent evidence indexed; failed cases prevent sign-off. | J68: Team lead | K68: Not started | M68: Pending | Q68: =IF(AND(K68="Done",M68="Accepted",LEN(L68)>0,LEN(P68)>0),1,0) | R68: F043, T023

Sheet Acceptance
A2: MatriSathi acceptance scenarios
A3: AT01–AT32 are this pack’s suite. Re-run affected cases at later gates and the release candidate.
A6: Case | B6: First gate | C6: Requirements | D6: Scenario | E6: Test steps | F6: Expected outcome | G6: Reviewer | H6: Result | I6: Evidence link | J6: Candidate SHA / date | K6: Actual reviewer
A7: AT01 | B7: SG1 | C7: R02 R07 | D7: Staff login and sessions | E7: Login with seeded staff; reject invalid/expired tokens; refresh, logout, replay and disable account. | F7: Valid session works; rotated/revoked sessions fail; generic errors and throttling evidenced. | G7: Tech lead | H7: Pass | I7: docs/delivery/evidence/SG1/report.md | J7: 2026-09-30 (uncommitted working tree, pending commit)
A8: AT02 | B8: SG1 | C8: R02 | D8: Organization and facility isolation | E8: Use two organizations, two facilities in one organization, coordinator and org admin; revoke membership. | F8: Allowed access only; org admin cannot cross organization; same token loses revoked access. | G8: Tech lead | H8: Pass | I8: docs/delivery/evidence/SG1/report.md | J8: 2026-09-30 (uncommitted working tree, pending commit)
A9: AT03 | B9: SG1 | C9: R02 | D9: Shared phone and reference injection | E9: Create two people sharing one phone; try linking an inaccessible Person into a new episode. | F9: People remain distinct; forbidden link and unauthorized search denied without exposing records. | G9: Tech lead | H9: Pass | I9: docs/delivery/evidence/SG1/report.md | J9: 2026-09-30 (uncommitted working tree, pending commit)
A10: AT04 | B10: SG1 | C10: R07 | D10: Audit integrity | E10: Create/read records; trigger denied request; try UPDATE/DELETE using runtime DB role. | F10: Successful and denied events persist with actor/time; runtime cannot alter history; no sensitive payloads. | G10: Tech lead | H10: Pass | I10: docs/delivery/evidence/SG1/report.md | J10: 2026-09-30 (uncommitted working tree, pending commit)
A11: AT05 | B11: SG1 | C11: R09 R10 | D11: Repeatable foundation | E11: Fresh checkout; locked install; migrations; real UI login/create/read; reload and restart. | F11: Documented commands succeed; persisted record shown; CI output tied to SHA. | G11: Tester | H11: Blocked | I11: docs/delivery/evidence/SG1/report.md | J11: 2026-09-30 (uncommitted working tree, pending commit); CI not run — no remote (see report §6)
A12: AT06 | B12: SG2 | C12: Stages 1–3 R05 | D12: Late/unknown dating and schedules | E12: Enter late pregnancy and unknown dates; clinician confirms/corrects dating; revise template. | F12: Unknown stays unknown; only approved plan activates; past events retained; obsolete reminders cancelled. | G12: Doctor | H12: Not run
A13: AT07 | B13: SG2 | C13: R03 | D13: Appointments and overdue work | E13: Request, confirm, miss, reschedule and cancel visit; assigned owner unavailable. | F13: One clear next action; stale reminders cancelled; owned follow-up and backup; no inferred non-adherence. | G13: Tester | H13: Not run
A14: AT08 | B14: SG2 | C14: Stage 2 R03 R07 | D14: Reports and medicine records | E14: Upload private report; record performed/received; unauthorized user tries clinical review. | F14: Upload is not review; only clinician marks review; original prescription retained; ambiguous instructions queued. | G14: Doctor | H14: Not run
A15: AT09 | B15: SG2 | C15: R03 | D15: Referral closure | E15: Record sent/contacted/attended/advice/follow-up; try closing only because message sent. | F15: Closure follows defined state or reason; owner and unresolved work visible. | G15: Doctor | H15: Not run
A16: AT10 | B16: SG2 | C16: Stage 3 R06 | D16: Birth plan and urgent help | E16: Open verified contact route without login/GPS; use web and printed plan. | F16: Dated contact, alternate and direct dialler available; no dispatch/ETA or chat emergency promise. | G16: Doctor | H16: Not run
A17: AT11 | B17: SG3 | C17: R01 | D17: Real outbound messaging | E17: Send approved template to consenting staff test handset; capture provider status callbacks. | F17: Actual receipt verified; submitted/delivered/failed distinguished; no patient data in evidence. | G17: Tech lead | H17: Not run
A18: AT12 | B18: SG3 | C18: R01 R10 | D18: Retries and stale sends | E18: Duplicate webhook/job; provider timeout; reschedule, opt out and restart worker. | F18: No repeated effect; unknown delivery reconciled; send-time eligibility checked; failures owned. | G18: Tech lead | H18: Not run
A19: AT13 | B19: SG3 | C19: R01 R02 | D19: Inbound media and identity | E19: Send real text/voice/photo; shared number ambiguous; unsupported/oversized upload. | F19: Restricted unlinked queue; staff confirms identity; original audio playable; fallback and owner present. | G19: Tester | H19: Not run
A20: AT14 | B20: SG3 | C20: R01 R06 | D20: Audio and channel preferences | E20: Play approved audio on web and permitted WhatsApp route; change language, safe timing, detail and opt-out. | F20: Text equivalent visible; preferences honored; fallback works; no generated clinical answer. | G20: Doctor | H20: Not run
A21: AT15 | B21: SG4 | C21: Stages 4–5 R02 | D21: Birth and twins | E21: Record birth with two children; update one child and leave other unchanged. | F21: Distinct identities and histories; unknown facts allowed; siblings unaffected. | G21: Pediatric reviewer | H21: Not run
A22: AT16 | B22: SG4 | C22: Stage 5 R04 | D22: Separate discharge | E22: Record mother and each child discharged on different dates with approved follow-up. | F22: Each approval and instructions independent; no metric automatically clears discharge. | G22: Doctor + Pediatric reviewer | H22: Not run
A23: AT17 | B23: SG4 | C23: R04 | D23: Loss and message pause | E23: Report loss while incompatible messages queued; confirm outcome; one twin affected. | F23: Pause applies immediately to unsent incompatible messages; final send rechecks; in-flight limit logged; maternal support and sibling retained. | G23: Doctor | H23: Not run
... A38: AT32 | B38: SG5 | C38: R07 R10 | D38: Files, logs and exports | E38: Test disallowed upload, signed-link expiry, spreadsheet-like input and sensitive log paths. | F38: Validated private files; minimal logs; safe scoped export; no secrets or patient text in diagnostics. | G38: Tech lead | H38: Not run

Sheet Capacity
A2: Weekly capacity and estimates
A3: Edit available hours to the confirmed commitment. Negative balance requires reassignment or a revised date.
A6: Week | B6: Role | C6: Available h | D6: Planned h | E6: Remaining h | F6: Action / decision
A7: 1 | B7: Team lead | C7: 10 | D7: =SUMIFS(Tasks!$E$7:$E$68,Tasks!$B$7:$B$68,A7,Tasks!$D$7:$D$68,B7) | E7: =C7-D7
A8: 1 | B8: Tech lead | C8: 10 | D8: =SUMIFS(Tasks!$E$7:$E$68,Tasks!$B$7:$B$68,A8,Tasks!$D$7:$D$68,B8) | E8: =C8-D8
A9: 1 | B9: Developer | C9: 25 | D9: =SUMIFS(Tasks!$E$7:$E$68,Tasks!$B$7:$B$68,A9,Tasks!$D$7:$D$68,B9) | E9: =C9-D9
A10: 1 | B10: Doctor | C10: 2 | D10: =SUMIFS(Tasks!$E$7:$E$68,Tasks!$B$7:$B$68,A10,Tasks!$D$7:$D$68,B10) | E10: =C10-D10
A11: 1 | B11: Tester | C11: 0 | D11: =SUMIFS(Tasks!$E$7:$E$68,Tasks!$B$7:$B$68,A11,Tasks!$D$7:$D$68,B11) | E11: =C11-D11
A12: 2 | B12: Team lead | C12: 10 | D12: =SUMIFS(Tasks!$E$7:$E$68,Tasks!$B$7:$B$68,A12,Tasks!$D$7:$D$68,B12) | E12: =C12-D12
A13: 2 | B13: Tech lead | C13: 10 | D13: =SUMIFS(Tasks!$E$7:$E$68,Tasks!$B$7:$B$68,A13,Tasks!$D$7:$D$68,B13) | E13: =C13-D13
A14: 2 | B14: Developer | C14: 25 | D14: =SUMIFS(Tasks!$E$7:$E$68,Tasks!$B$7:$B$68,A14,Tasks!$D$7:$D$68,B14) | E14: =C14-D14
A15: 2 | B15: Doctor | C15: 2 | D15: =SUMIFS(Tasks!$E$7:$E$68,Tasks!$B$7:$B$68,A15,Tasks!$D$7:$D$68,B15) | E15: =C15-D15
A16: 2 | B16: Tester | C16: 4 | D16: =SUMIFS(Tasks!$E$7:$E$68,Tasks!$B$7:$B$68,A16,Tasks!$D$7:$D$68,B16) | E16: =C16-D16
A17: 3 | B17: Team lead | C17: 10 | D17: =SUMIFS(Tasks!$E$7:$E$68,Tasks!$B$7:$B$68,A17,Tasks!$D$7:$D$68,B17) | E17: =C17-D17
A18: 3 | B18: Tech lead | C18: 10 | D18: =SUMIFS(Tasks!$E$7:$E$68,Tasks!$B$7:$B$68,A18,Tasks!$D$7:$D$68,B18) | E18: =C18-D18
... A46: 8 | B46: Tester | C46: 8 | D46: =SUMIFS(Tasks!$E$7:$E$68,Tasks!$B$7:$B$68,A46,Tasks!$D$7:$D$68,B46) | E46: =C46-D46
A49: Eight-week total by role
A50: Role | B50: Available h | C50: Planned h | D50: Remaining h
A51: Team lead | B51: =SUMIF(B7:B46,A51,C7:C46) | C51: =SUMIF(B7:B46,A51,D7:D46) | D51: =B51-C51
A52: Tech lead | B52: =SUMIF(B7:B46,A52,C7:C46) | C52: =SUMIF(B7:B46,A52,D7:D46) | D52: =B52-C52
A53: Developer | B53: =SUMIF(B7:B46,A53,C7:C46) | C53: =SUMIF(B7:B46,A53,D7:D46) | D53: =B53-C53
A54: Doctor | B54: =SUMIF(B7:B46,A54,C7:C46) | C54: =SUMIF(B7:B46,A54,D7:D46) | D54: =B54-C54
A55: Tester | B55: =SUMIF(B7:B46,A55,C7:C46) | C55: =SUMIF(B7:B46,A55,D7:D46) | D55: =B55-C55
A57: Doctor time is fully allocated. Pediatric, language and live support capacity must be confirmed separately.

Sheet Decisions
A2: Decisions and dependencies
A3: Resolve each item before its due gate; proposed direction is not an approval.
A6: ID | B6: Due gate | C6: Owner | D6: Decision needed | E6: Proposed direction | F6: Status | G6: Decision / rationale | H6: Approved by / date | I6: Evidence link
A7: D01 | B7: SG0 | C7: Team lead | D7: Exact weekly hours and named owners | E7: Use 10h lead, 10h tech, 25h developer planning baseline; confirm developer 20–25h allocation. | F7: Open
A8: D02 | B8: SG0 | C8: Team lead + Doctor | D8: Pilot sites, language and reviewers | E8: One rural and one semi-urban setting; English plus one selected local language; named pediatric reviewer. | F8: Open
A9: D03 | B9: SG0 | C9: Team lead | D9: Shared repository policy and delegated authority | E9: Adopt task branches, PR review and human commit/push approvals; select merge approver. | F9: Open
A10: D04 | B10: SG1 | C10: Tech lead | D10: Auth/session, runtime and dependency versions | E10: Password staff login; reviewed session design; pinned supported versions and current dependency review. | F10: Open | G10: PROPOSED (pending Tech Lead approval): password staff login; 15-min access token + 14-day rotating refresh with reuse detection; Python 3.12.14 pinned via uv.lock; Node 26.8.1 pinned via .nvmrc; all dependencies pinned exactly. See report §5 (M003 review evidence). | I10: docs/delivery/evidence/SG1/report.md
A11: D05 | B11: SG2 | C11: Doctor + Pediatric reviewer | D11: Clinical templates and urgent wording | E11: Approve source/version/local applicability; no universal schedule by resource tier. | F11: Open
A12: D06 | B12: SG2 | C12: Team lead + Tech lead | D12: WhatsApp provider/account and budget | E12: Compare current direct/provider costs, onboarding and media support; no vendor selected by this pack. | F12: Open
A13: D07 | B13: SG2 | C13: Tech lead + Team lead | D13: Patient verification and caregiver mechanism | E13: No phone-only household access; agree revocation and assisted flow before patient rollout. | F13: Open
A14: D08 | B14: SG3 | C14: Team lead | D14: Language recording and testing capacity | E14: Assign language-capable narrator/reviewer; tester 40h across plan; pediatric time separate from gynecologist 2h/week. | F14: Open
A15: D09 | B15: SG5 | C15: Team lead + Facility owner | D15: Hosting, retention, vendor data flows and rights | E15: Document review applicable to pilot date; India hosting is proposed policy, not legal certification. | F15: Open
A16: D10 | B16: SG5 | C16: Team lead + Tech lead | D16: Recovery, load and operating cost thresholds | E16: Approve proposed RPO/RTO and load targets; set monthly INR budget, alert and send-stop limits. | F16: Open
A17: D11 | B17: SG6 | C17: Facility owner + Team lead | D17: Live support roster and response commitments | E17: Name coordinator, backup and clinical escalation before any real enrolment. | F17: Open
A18: D12 | B18: SG7 | C18: Team lead + Doctor + Tech lead | D18: Pilot authorization | E18: Separate technical, clinical and operations acceptance; pilot deployment and real enrolment need explicit authorization. | F18: Open

Sheet Traceability
A2: Requirements to build and test
A3: Source: MatriSathi_Specifications_Updated.xlsx v2, 28 Sep 2026; standalone amendments in baseline §1.
A6: Requirement | B6: Required scope | C6: Gates | D6: Implementation tasks | E6: Acceptance cases
A7: Stage 1 | B7: Pregnancy confirmation and entry | C7: SG1 SG2 | D7: M004–M006 M011 M013 | E7: AT03 AT05 AT06
A8: Stage 2 | B8: Routine pregnancy care | C8: SG2 | D8: M011 M012 | E8: AT06 AT07 AT08 AT09
A9: Stage 3 | B9: Delivery readiness | C9: SG2 | D9: M013 M015 | E9: AT10
A10: Stage 4 | B10: Labour/birth documentation | C10: SG4 | D10: M027 M028 | E10: AT15 AT18
A11: Stage 5 | B11: Separate discharge | C11: SG4 | D11: M027 M031 | E11: AT16
A12: Stage 6 | B12: Early postpartum | C12: SG4 | D12: M029 M031 | E12: AT16 AT17 AT18
A13: Stage 7 | B13: Infancy | C13: SG5 | D13: M035 M039 | E13: AT19 AT29
A14: Stage 8 | B14: Early childhood | C14: SG5 | D14: M035 M039 | E14: AT19 AT29
A15: R01 | B15: WhatsApp and voice | C15: SG3 | D15: M017–M024 | E15: AT11 AT12 AT13 AT14
A16: R02 | B16: Identity and caregiver access | C16: SG1 SG2 SG4 SG5 | D16: M003 M005 M010 M025 M034 M037 | E16: AT01 AT02 AT03 AT28 AT29
A17: R03 | B17: Tasks, tests and referrals | C17: SG2 SG5 | D17: M009 M011 M012 M044 | E17: AT07 AT08 AT09 AT23
... A26: R12 | B26: Pilot evidence and impact | C26: SG5 SG6 SG7 | D26: M044 M053 M055 M060 | E26: AT23 AT24 AT26

Sheet Functional Specs
A2: MatriSathi functional requirements by gate
A3: Version 1.1 | Filter Gate for the required build scope. Existing task dates/hours remain unchanged. Named approvals are still required.
A4: Gate is the first delivery/verification milestone; controls continue afterward. Open mechanisms and proposed targets need a Decisions tab record.
A5: Sources: MatriSathi_Specifications_Updated.xlsx v2 + MatriSathi_Functional_Technical_Baseline.docx v1.0 (28 Sep 2026), including standalone amendments.
A6: Spec ID | B6: Gate | C6: Day | D6: Feature / screen | E6: Users | F6: Detailed functionality to build | G6: Required data | H6: Workflow rules and exceptions | I6: Rural / semi-urban use | J6: What to demonstrate | K6: Linked task IDs | L6: Acceptance cases | M6: Delivery owner | N6: Required approval / open decision | O6: Source requirement
A7: F001 | B7: SG0 | C7: 2 | D7: Adopt scope and delivery rules | E7: Team lead; tech lead; doctor | F7: Confirm the eight care stages, shared requirements, pilot language, two settings, named reviewers and team hours. Record accepted versions and first-stage authorization. | G7: Scope version; owner names; capacity; site/language; reviewer; approved stage; decision date. | H7: Standalone application. Essential journeys work without AI. Clinical content needs named approval. Keep required scope; estimate changes are explicit. | I7: Same essential care/privacy features for NGO/PHC and private sites. Billing automation is deferred. | J7: SG0 decision record names owners, language, reviewer, capacity and accepted amendments. | K7: M001 M002 | L7: SG0 evidence | M7: Team lead | N7: D01 D02 D03; team lead accepts baseline. | O7: Baseline §1, §9; R09–R12 as amended
A8: F002 | B8: SG1 | C8: 7 | D8: People and pregnancy registration | E8: Coordinator; authorized patient; clinician | F8: Find an authorized record or create a person, capture available intake and create a separate pregnancy episode. Save and reopen the same record after reload. | G8: Person ID; episode ID; owning facility; name; available age/DOB with precision; history; existing medicines/allergies; source; available dates. | H8: Keep missing history unknown. Do not infer normal findings, risk or diagnosis. No mandatory Aadhaar, ABHA, email or smartphone. Enforce authorized person linking. | I8: Assisted entry for low-literacy/no-phone users; responsive self-entry where enabled. Available MCP records may be attached in SG2. | J8: Register early, late and unknown-date cases; reopen persisted record; reject inaccessible person links. | K8: M004 M005 M006 M008 | L8: AT03 AT05; AT06 at SG2 | M8: Developer | N8: Doctor validates intake; tech lead approves identity design. | O8: Stage 1; R02 R09; Baseline §2–3, §7
A9: F003 | B9: SG1 | C9: 7 | D9: Shared phones and contact changes | E9: Patient; coordinator | F9: Store contact separately from person identity. Confirm which person a contact relates to and record safe preferences. Review suspected duplicates manually. | G9: Contact value; linked person; verification evidence/status; preferred language; contact owner; change actor/date. | H9: A phone number may belong to several people. Never merge by number or transfer identity on number change. Uncertain identity cannot expose records. | I9: Support shared family handsets and no-phone assisted contact. No household-wide access from possession of a number. | J9: Two women with one number have independent records; number change does not grant another person access. | K9: M003 M005 M006 | L9: AT02 AT03 | M9: Developer | N9: Tech lead reviews reference and search permissions. | O9: R02; Stage 1; Baseline §2, §7
A10: F004 | B10: SG1 | C10: 7 | D10: Staff roles and assigned records | E10: Org admin; coordinator; ASHA; ANM/nurse; doctor | F10: Admin manages authorized memberships. Staff sees only facilities and records permitted by role and assignment. Clinician-only actions are reserved for clinical users. | G10: Organization; facility; staff membership; capabilities; assignment; active/revoked state; audit actor. | H10: Admin role alone gives no clinical-record access. ASHA cannot approve a clinical plan or mark report review. Revocation affects subsequent requests. | I10: Assign workers according to actual training, availability and equipment; no village-wide access assumption. | J10: Compare doctor, field worker and admin views in two organizations; revoke membership and retry access. | K10: M003 M005 M008 | L10: AT01 AT02 AT03 AT04 | M10: Developer | N10: Doctor confirms field role boundaries; tech lead confirms enforcement. | O10: R02 R05 R07; Baseline §2, §8
A11: F005 | B11: SG2 | C11: 14 | D11: Dating and local care plans | E11: Doctor; authorized coordinator; patient | F11: Record provisional dating and its source. Clinician confirms or corrects dating and activates a versioned local ANC plan with individual exceptions. Publish future care actions. | G11: Episode; LMP/other dating if supplied; source/precision; confirmation; template/version; approver; effective date; individual dates. | H11: Unknown dates stay unknown. Do not invent previous visits. Correcting dates preserves historical care and cancels/replaces obsolete future reminders. Resource tier does not select a clinical standard. | I11: Works at first contact at any gestation. Only locally adopted schedules and actually available appointments are shown. | J11: Late and unknown-date entry works; clinician changes date/plan; completed events stay intact and old reminders stop. | K11: M009 M011 M015 | L11: AT06 | M11: Developer | N11: D05; doctor approves actual schedule, sources and wording. | O11: Stage 1–3; R05; Baseline §3, §5
A12: F006 | B12: SG2 | C12: 14 | D12: Patient next-action view | E12: Patient; delegated caregiver; coordinator | F12: Show the next confirmed action, date/location if known, preparation, status and help route. Let the person report done, not done or need help and request a callback. | G12: Subject; approved action; due date/status; preparation version; contact; reported response; barrier; last update. | H12: Keep patient-reported completion distinct from staff verification. Missing logs stay unknown. Do not infer non-adherence or clinical urgency. | I12: Large controls and plain language. Staff can explain and print next steps; phone/assisted fallback when data is unavailable. | J12: Patient identifies next action and help route; staff sees a help request with owner and context. | K12: M011 M013 | L12: AT07 AT10 AT28 | M12: Developer | N12: Doctor reviews preparation; team lead reviews usability. | O12: Stages 1–3; R03 R06; Baseline §2–3
A13: F007 | B13: SG2 | C13: 14 | D13: Appointments and rescheduling | E13: Patient; coordinator; clinic staff | F13: Request an appointment, confirm actual date/site, record attendance or missed visit, and reschedule/cancel. Create an owned follow-up after a missed visit. | G13: Appointment ID; subject; requested/confirmed time; facility/contact; status; prior appointment; owner; reason. | H13: States: requested, confirmed, attended, missed, rescheduled, cancelled. Preserve old event; cancel obsolete reminders. Booking is a request until a person confirms. | I13: No assumption of live hospital scheduling integration. Staff confirms local clinic/community availability manually. | J13: Miss a visit, assign follow-up, reschedule once and show only the current reminder is eligible. | K13: M009 M011 M016 | L13: AT07 | M13: Developer | N13: Doctor and coordinator validate actual booking workflow. | O13: Stage 2; R03 R05; Baseline §5
A14: F008 | B14: SG2 | C14: 14 | D14: Owned tasks and practical barriers | E14: Coordinator; ASHA; ANM/nurse; patient | F14: Assign follow-up, record due time, contact attempt and patient barriers, and close with result/reason. Reassign unavailable staff and overdue work to a backup. | G14: Task type; subject; owner/backup; due time; state; attempt time; travel/cost/medicine-access barrier; closure reason. | H14: States: new, assigned, awaiting patient, completed, cancelled. Declined, unreachable and unknown remain distinct outcomes. Overdue means administrative delay, not clinical risk. | I14: No daily field visits or kit availability assumed. Use actual staff acceptance and facility fallback. | J14: Unavailable worker and unreachable family both retain owned unresolved work; completion has recorded outcome. | K14: M009 M011 M029 M044 | L14: AT07 AT23 AT27 | M14: Developer | N14: Doctor validates role limits; facility confirms available owners. | O14: R03 R05 R11; Baseline §5
A15: F009 | B15: SG2 | C15: 14 | D15: Investigations and report review | E15: Patient; nurse; coordinator; clinician | F15: Record requested tests, performed event, report receipt/upload and clinical review as separate steps. Route missing records and review work to named staff. | G15: Test/request; request/performed/received dates; source; private file; reviewing clinician/date; next approved action. | H15: Requested → performed → received → reviewed. A received outside report may have unknown earlier dates; retain them as unknown. Only an authorized clinician records review. No report interpretation. | I15: Accept available paper/MCP photos or PDFs through staff-assisted upload; preserve originals. | J15: Upload is displayed as received, not reviewed; non-clinician review attempt fails; clinician review is attributable. | K15: M009 M012 M016 | L15: AT08 AT32 | M15: Developer | N15: Doctor approves review workflow. | O15: Stage 2; R03 R07; Baseline §3, §5
A16: F010 | B16: SG2 | C16: 14 | D16: Existing prescriptions and reminders | E16: Patient; caregiver with grant; clinician; coordinator | F16: Display an already issued prescription and set a reminder only from confirmed instructions. Route unclear medicine instructions to a clinician. | G16: Original prescription/source/date; confirmed instruction; clinician/confirmation; reminder timing; start/end if supplied; pause. | H16: Do not suggest drugs, calculate dose/duration or rewrite prescriptions. Keep changes and originals traceable. Uncertainty blocks the affected reminder until reviewed. | I16: Support assisted reading and approved medicine-use education. Record availability/cost barriers as help requests. | J16: Known instruction produces the agreed reminder; ambiguous instruction creates review work without invented dosing. | K16: M012 M021 | L16: AT08 AT12 AT14 | M16: Developer | N16: Doctor confirms instruction and patient wording. | O16: Stage 2; R03 R06; Baseline §3, §7
A17: F011 | B17: SG2 | C17: 14 | D17: Referrals and return advice | E17: Clinician; coordinator; receiving team | F17: Record clinician-selected destination and urgency, contact the receiving service, track attendance and returned advice, and assign resulting follow-up. | G17: Referral ID; subject; destination/contact; clinician instruction; receiving owner; sent/contacted/attended/advice dates; closure reason. | H17: States: sent, contacted, attended, advice received, follow-up completed, or explicit closure reason. A message sent does not close the referral. No automatic specialist/risk matching. | I17: Use verified local services, phone calls and manual external records; no hospital-system integration required. | J17: Demonstrate missed attendance, return advice and open follow-up; close only with defined outcome/reason. | K17: M012 M016 M028 | L17: AT09 AT18 | M17: Developer | N17: Doctor validates referral destination/urgency and closure meaning. | O17: Stages 2, 6–8; R03 R04; Baseline §5
A18: F012 | B18: SG2 | C18: 14 | D18: Raw observations and clinician findings | E18: Authorized nurse; clinician; coordinator | F18: Record available dated observations and source records; show measurement history and clinician-entered findings alongside the next approved action. | G18: Observation name; raw value; unit; actual service date; entry date; source; recorder; clinician finding if supplied. | H18: No threshold alerts, inferred high risk, fetal growth interpretation or automatic non-adherence. Preserve unknown values; correction records reason and prior value. | I18: Only measurements actually taken with available equipment and trained staff are entered. | J18: Enter a measurement and external finding; no generated judgment appears; date/unit/source remain visible. | K18: M012 M015 | L18: AT08 AT31 | M18: Developer | N18: Doctor approves allowed fields and units before use. | O18: Stage 2; G07; R03 R05; Baseline §7
... A50: F043 | B50: SG7 | C50: 56 | D50: Pilot release and training | E50: Team lead; tech lead; doctor; pediatric reviewer; tester | F50: Demonstrate complete journey, train staff, package setup/support instructions and obtain separate technical, clinical and operating decisions for the candidate release. | G50: Candidate SHA; baseline versions; test evidence; clinical approvals; training record; support/recovery plan; defects; go/no-go. | H50: All required stages/shared functions and AT01–AT32 evidenced. Critical/high defects block. Deployment and patient enrolment need authorization; Day 57–60 reserve is for corrections. | I50: Train on real rural/semi-urban workflows, shared phones, manual fallback and loss/transfer cases. | J50: Fresh setup and full acceptance pass; three sign-offs identify candidate and approved pilot boundaries. | K50: M056 M057 M058 M059 M060 M061 M062 | L50: AT01–AT32 | M50: Team lead | N50: D12; separate clinical, technical and operating sign-offs. | O50: R10 R11 R12; Baseline §9; Delivery plan SG7

Sheet Technical Specs
A2: MatriSathi technical build specifications by gate
A3: Version 1.1 | Filter Gate for the required build scope. Existing task dates/hours remain unchanged. Named approvals are still required.
A4: Gate is the first delivery/verification milestone; controls continue afterward. Open mechanisms and proposed targets need a Decisions tab record.
A5: Sources: MatriSathi_Specifications_Updated.xlsx v2 + MatriSathi_Functional_Technical_Baseline.docx v1.0 (28 Sep 2026), including standalone amendments.
A6: Spec ID | B6: Gate | C6: Day | D6: Component / area | E6: Implementation requirement | F6: Data / interface contract | G6: Controls and constraints | H6: Failure / exception behavior | I6: Verification required | J6: Linked task IDs | K6: Acceptance cases | L6: Delivery owner | M6: Required decision / approval | N6: Source requirement
A7: T001 | B7: SG0 | C7: 2 | D7: Architecture and repository boundary | E7: Adopt one standalone responsive frontend/backend path and bounded stage delivery. Essential functionality has no dependency on optional AI. | F7: Proposed React/Vite/TypeScript; FastAPI modular backend; PostgreSQL/Alembic; private object storage; durable worker. Confirm at SG0/SG1. | G7: Work only in current repository. No other-platform schema, authentication, code or brand dependency. No native app, microservice fleet or websocket requirement. | H7: If the persisted first slice cannot be proved by SG1, record capacity/date impact rather than silently changing scope. | I7: Approved architecture record and SG1 real browser persistence proof. | J7: M001 M002 M004 M006 | K7: AT05 AT31 | L7: Tech lead | M7: D01 D03 D04; stack is a proposed baseline until adopted. | N7: R09 amended; Baseline §1, §6
A8: T002 | B8: SG1 | C8: 7 | D8: API contracts and validation | E8: Version APIs and agree request/response schemas before dependent frontend/backend work. | F8: /api/v1; OpenAPI; consistent error shapes; paging; bounded queries; operation IDs for retryable creates/uploads/effects; entity version on updates. | G8: Derive organization/facility from current server permissions; never trust client subject/reference IDs. Separate clinical event date from entry time. | H8: Reject invalid references/versions with actionable errors that do not leak inaccessible record existence. | I8: Contract tests cover rejected cross-scope references, pagination and correct persisted response. | J8: M003 M004 M005 M009 | K8: AT02 AT03 AT05 | L8: Tech lead | M8: D04; tech lead approves concrete contracts by task. | N8: R02 R09; Baseline §6–7
A9: T003 | B9: SG1 | C9: 7 | D9: Core schema and invariants | E9: Create only first-slice tables initially; add later entities in their assigned stages using reviewed migrations. | F9: Organization; Facility(org); StaffUser; Membership; Session; Person; ContactMethod; PregnancyEpisode(mother, facility, dating/source, status). Stable IDs; created/updated/version. | G9: Validate ownership/sharing and foreign keys. Phone is not unique person identity. Use explicit unknown/precision; do not substitute zero, today or assumed normal. | H9: Reject inaccessible person linking. Keep corrected history and original service/source information. | I9: Migration from empty DB works; two people share phone; wrong-person reference fails. | J9: M003 M004 M005 | K9: AT02 AT03 AT05 | L9: Developer | M9: Tech lead approves Person ownership and migration invariants. | N9: R02 R09; Baseline §7
A10: T004 | B10: SG1 | C10: 7 | D10: Staff authentication and sessions | E10: Implement staff login, refresh, logout, expiry, account disable and replay handling. | F10: Unique login; reviewed password hash; short access session; rotated refresh/token identifiers; expiry/revocation/lineage; current membership. | G10: Generic authentication errors; bounded throttling; no production seed credentials. Document browser token storage, cookie/CSRF protections as applicable. | H10: Logout, disabled user, revoked membership and refresh replay invalidate subsequent access; no process-local membership cache as authority. | I10: AT01 with real DB/session behavior plus current-membership enforcement in AT02. | J10: M003 M005 | K10: AT01 AT02 | L10: Developer | M10: D04 fixes mechanism, lifetimes and supported versions before build. | N10: R02 R07; Baseline §8
A11: T005 | B11: SG1 | C11: 7 | D11: Authorization and database roles | E11: Enforce organization, facility, role and subject scope on every read/write/search/link/file/export. | F11: Central authorization checks plus relational constraints; separate migration-owner and restricted runtime DB credentials. | G11: No automatic clinical access from admin title. Enforce clinical-only actions and record grants. Denied logs survive business transaction rollback. | H11: Reject guessed IDs and cross-organization references without exposing record existence. Runtime cannot edit/delete audit history. | I11: Direct API/search/reference and DB-role tests; membership revoke uses same existing token. | J11: M003 M005 M010 M018 M041 M050 | K11: AT02 AT03 AT04 AT28 AT32 | L11: Developer | M11: Tech lead reviews sensitive access changes independently. | N11: R02 R07; Baseline §2, §7–8
A12: T006 | B12: SG1 | C12: 7 | D12: Audit foundation and safe diagnostics | E12: Capture successful/denied access and important state changes with minimal attributable metadata. | F12: Actor; UTC system time; entity/action; scoped reference; reason; version/request ID. Clinical event time is separate. | G12: No patient text, voice, phone numbers, secrets or identifiers in ordinary diagnostics. Restricted audit access; routine users cannot change history. | H12: Audit for denied operation survives rollback. Privileged maintenance is explicitly controlled; do not claim absolute immutability. | I12: Exercise denial, success, runtime UPDATE/DELETE and sensitive error path. | J12: M003 M005 M043 | K12: AT04 AT32 | L12: Developer | M12: Tech lead approves fields, access and retention with D09. | N12: R07; Baseline §8
A13: T007 | B13: SG1 | C13: 7 | D13: Reproducible setup and CI | E13: Create locked installs, documented local setup, test fixtures and CI for reviewed shared work. | F13: Pinned supported runtimes/dependencies; PostgreSQL-backed tests; Python lint/type/tests; frontend lint/type/build; browser smoke; empty-DB migration; secret/dependency checks. | G13: Synthetic development data only. Separate contributor checkouts/task branches; required review/CI or documented manual equivalent. Existing approval policy applies. | H13: Failed checks prevent task acceptance; list checks not run. Do not weaken tests to make CI pass. | I13: Fresh checkout runs documented commands and real persisted UI journey; evidence tied to SHA. | J13: M002 M004 M006 M059 | K13: AT05 | L13: Developer | M13: D03 D04; commits/pushes follow recorded human authority. | N13: R09 R10; Baseline §9; Delivery plan §5
A14: T008 | B14: SG2 | C14: 14 | D14: Plans, typed work and state transitions | E14: Implement distinct clinical-plan, appointment, task, investigation and referral state rules with current owner/version. | F14: Plan(template version, approver, effective date, exceptions); Task(owner, due, state, reason); Appointment; Investigation; Referral; original files/events. | G14: Validate each transition and role. Clinical plan activation/review belongs to clinician. Administrative urgency must not become clinical risk scoring. | H14: Dating/reschedule correction preserves history and cancels superseded future actions/reminders atomically with durable intent as applicable. | I14: Exercise late dates, missed appointments, upload-not-review, referral closure and stale reminder cancellation. | J14: M009 M011 M012 | K14: AT06 AT07 AT08 AT09 | L14: Developer | M14: D05; doctor approves schedule semantics and clinical-only transitions. | N14: R03 R05; Baseline §5–7
A15: T009 | B15: SG2 | C15: 14 | D15: Private uploads and downloads | E15: Store files privately with authenticated, subject-scoped access and clear upload/receipt states. | F15: File ID; organization/subject; source; type; size; validated object key; checksum where used; upload status; authorized short-lived download. | G15: Validate content/type/size; safe filenames; no public record bucket or long-lived public clinical URL. Shared-phone links need subject authorization. | H15: Unsupported/failed upload remains failed with fallback; expired/revoked/unauthorized downloads fail. | I15: Report/media upload plus guessed ID, expired link and unsupported-type tests. | J15: M009 M012 M018 M020 M043 | K15: AT08 AT13 AT22 AT32 | L15: Developer | M15: Tech lead chooses reviewed file limits and access mechanism. | N15: R01 R07; Baseline §8
A16: T010 | B16: SG2 | C16: 14 | D16: Patient and delegated access contract | E16: Specify identity verification, recovery, session and grant behavior before building patient access. | F16: Person/subject session; verifier/evidence; CaregiverGrant(subject, grantee, scope, grantor, expiry, revocation); child authority extends at SG4/SG5. | G16: Phone possession is not authorization. Verify current grant on record, search and download; protect shared-device sessions. | H16: Ambiguous identity stays restricted. Number changes never silently transfer access. Revocation denies next authorized request. | I16: Two women/one phone, another handset user, caregiver revoke and unverified guardian tests. | J16: M010 M013 M034 M037 | K16: AT28 AT29 AT22 | L16: Tech lead | M16: D07 is a blocking design decision; mechanism not pre-approved. | N16: R02 R07; Baseline §2, §7–8
A17: T011 | B17: SG3 | C17: 21 | D17: Provider adapter and authenticated callbacks | E17: Use one official WhatsApp provider behind an adapter; verify current rules during setup. | F17: Outbound template send; provider IDs/status mapping; signature-verified webhook; inbound text/audio/photo; normalized status and error events. | G17: Keep credentials server-side; validate callback signature and deduplicate provider event IDs. Restrict unlinked media/message queue. | H17: Out-of-order/duplicate callbacks cannot create duplicate business effects or regress terminal status incorrectly; uncertain delivery requires reconciliation. | I17: Real test handset receipt and real inbound media; reject invalid webhook; replay callback without duplicate work. | J17: M017 M018 M019 M020 M024 | K17: AT11 AT12 AT13 | L17: Developer | M17: D06; provider onboarding, template approval and media rules verified. | N17: R01 R10; Baseline §5, §8
A18: T012 | B18: SG3 | C18: 21 | D18: Durable jobs and send eligibility | E18: Persist intent with business change and process with durable claims/leases, bounded retries and an owned failure queue. | F18: Job/outbox ID; operation key; subject/recipient; content/plan version; eligibility; scheduled time; lease; attempts; provider ID; terminal reason. | G18: Before sending recheck current permission, recipient, plan, content and pause. Correctness cannot depend on in-memory jobs or counters. | H18: Worker crash/retry cannot repeat effect. Unknown provider acceptance is reconciled rather than blind resend. Cancel obsolete intent; retain audit/failure owner. | I18: Duplicate callback/job, timeout and worker restart tests at SG3; two-worker/crash suite at SG5. | J18: M017 M019 M044 | K18: AT12 AT30 | L18: Developer | M18: Tech lead approves retry/lease/timeout/reconciliation policy. | N18: R01 R10; Baseline §6, §8
... A29: T023 | B29: SG7 | C29: 56 | D29: Release evidence and change control | E29: Tie mandatory tests, content approvals, setup and operational sign-offs to one candidate SHA. | F29: Baseline/version; M/F/T/AT mapping; CI and demo evidence; doctor feedback; open defects; reviewer; release/rollback plan; authorization. | G29: No critical/high open defects. No gate auto-passes from task counts. Evidence reuse requires affected-code assessment. Keep patient data/secrets out of reports. | H29: Failed mandatory check holds affected release. Days 57–60 are correction reserve; new features need re-estimation. | I29: Fresh setup, all AT01–AT32 current, independent review and separate technical/clinical/operating sign-offs. | J29: M056 M057 M058 M059 M060 M061 M062 | K29: AT01–AT32 | L29: Tech lead | M29: D12; team authorizes deployment/enrolment separately. | N29: R10–R12; Baseline §9; Delivery plan SG7
